slurm_workflow_utils/__init__.py
slurm_workflow_utils/builder.py
slurm_workflow_utils/console_helper.py
slurm_workflow_utils/constants.py
slurm_workflow_utils/file_utils.py
slurm_workflow_utils/launcher.py
slurm_workflow_utils/system_caller.py
slurm_workflow_utils/workflow_builder.py
slurm_workflow_utils/workflow_launcher.py
slurm_workflow_utils-0.1.0.dist-info/AUTHORS.rst
slurm_workflow_utils-0.1.0.dist-info/LICENSE
slurm_workflow_utils-0.1.0.dist-info/METADATA
slurm_workflow_utils-0.1.0.dist-info/WHEEL
slurm_workflow_utils-0.1.0.dist-info/entry_points.txt
slurm_workflow_utils-0.1.0.dist-info/top_level.txt
slurm_workflow_utils-0.1.0.dist-info/RECORD
